iniesta/__init__.py
iniesta/app.py
iniesta/choices.py
iniesta/cli.py
iniesta/config 2.py
iniesta/config.py
iniesta/exceptions.py
iniesta/listeners.py
iniesta/log.py
iniesta/messages.py
iniesta/sessions.py
iniesta/utils.py
iniesta/sns/__init__.py
iniesta/sns/client.py
iniesta/sns/message.py
iniesta/sqs/__init__.py
iniesta/sqs/client.py
iniesta/sqs/message.py
insanic_iniesta-0.4.0.dist-info/LICENSE
insanic_iniesta-0.4.0.dist-info/METADATA
insanic_iniesta-0.4.0.dist-info/WHEEL
insanic_iniesta-0.4.0.dist-info/entry_points.txt
insanic_iniesta-0.4.0.dist-info/top_level.txt
insanic_iniesta-0.4.0.dist-info/RECORD
