Metadata-Version: 2.1
Name: insanic-iniesta
Version: 0.4.0
Summary: Messaging integration for insanic
Home-page: https://github.com/crazytruth/iniesta
Author: Kwang Jin Kim
Author-email: kwangjinkim@gmail.com
License: MIT
Keywords: iniesta insanic sanic async asyncio aws sqs sns event python3
Platform: UNKNOWN
Classifier: Development Status :: 2 - Pre-Alpha
Classifier: Intended Audience :: Developers
Classifier: License :: OSI Approved :: MIT License
Classifier: Programming Language :: Python :: 3.6
Classifier: Programming Language :: Python :: 3.7
Classifier: Programming Language :: Python :: 3.8
Requires-Dist: insanic-framework
Requires-Dist: aiobotocore (>=0.12.0)
Requires-Dist: aioredlock
Provides-Extra: cli
Requires-Dist: Click (>=7.0) ; extra == 'cli'
